xplain/__init__.py
xplain/attribute.py
xplain/dimension.py
xplain/query_config.py
xplain/xobject.py
xplain/xsession.py
xplain-0.0.35.dist-info/LICENSE
xplain-0.0.35.dist-info/METADATA
xplain-0.0.35.dist-info/WHEEL
xplain-0.0.35.dist-info/top_level.txt
xplain-0.0.35.dist-info/RECORD
