Metadata-Version: 2.1
Name: xplain
Version: 0.0.35
Summary: A xplain python package
Home-page: https://xplain-data.com
Author: Xplain Data
Author-email: peide.wang@xplain-data.com
Classifier: Programming Language :: Python :: 3
Classifier: License :: OSI Approved :: BSD License
Classifier: Operating System :: OS Independent
Requires-Python: >=3.6
License-File: LICENSE
Requires-Dist: pandas
Requires-Dist: requests
Requires-Dist: treelib
Requires-Dist: patsy
Requires-Dist: statsmodels
Requires-Dist: pyecharts
